LICENSE
README.md
texasholdem/__init__.py
texasholdem/agents/__init__.py
texasholdem/agents/basic.py
texasholdem/card/__init__.py
texasholdem/card/card.py
texasholdem/card/deck.py
texasholdem/evaluator/__init__.py
texasholdem/evaluator/evaluator.py
texasholdem/evaluator/lookup_table.py
texasholdem/game/__init__.py
texasholdem/game/action_type.py
texasholdem/game/game.py
texasholdem/game/hand_phase.py
texasholdem/game/history.py
texasholdem/game/move.py
texasholdem/game/player_state.py
texasholdem/gui/__init__.py
texasholdem/gui/abstract_gui.py
texasholdem/gui/text_gui.py
texasholdem/util/__init__.py
texasholdem/util/errors.py
texasholdem/util/functions.py
texasholdem-0.9.0.dist-info/LICENSE
texasholdem-0.9.0.dist-info/METADATA
texasholdem-0.9.0.dist-info/WHEEL
texasholdem-0.9.0.dist-info/RECORD
