Metadata-Version: 2.1
Name: texasholdem
Version: 0.9.0
Summary: A texasholdem python package
Home-page: https://github.com/SirRender00/texasholdem
License: MIT
Keywords: texasholdem,holdem,poker
Author: Evyn Machi
Author-email: evyn.machi@gmail.com
Requires-Python: >=3.8,<4.0
Classifier: License :: OSI Approved :: MIT License
Classifier: Programming Language :: Python :: 3
Classifier: Programming Language :: Python :: 3.8
Classifier: Programming Language :: Python :: 3.9
Classifier: Programming Language :: Python :: 3.10
Classifier: Programming Language :: Python :: 3.11
Requires-Dist: Deprecated (>=1.2.13,<2.0.0)
Requires-Dist: windows-curses (>=2.3.1,<3.0.0) ; sys_platform == "win32"
Project-URL: Bug Tracker, https://github.com/SirRender00/texasholdem/issues
Project-URL: Documentation, https://texasholdem.readthedocs.io/en/stable/
Project-URL: Repository, https://github.com/SirRender00/texasholdem
Project-URL: Wiki, https://github.com/SirRender00/texasholdem/wiki
